chik/__init__.py
chik/__main__.py
chik/_tests/README.md
chik/_tests/__init__.py
chik/_tests/blockchain/__init__.py
chik/_tests/blockchain/blockchain_test_utils.py
chik/_tests/blockchain/config.py
chik/_tests/blockchain/test_augmented_chain.py
chik/_tests/blockchain/test_blockchain.py
chik/_tests/blockchain/test_blockchain_transactions.py
chik/_tests/blockchain/test_build_chains.py
chik/_tests/blockchain/test_get_block_generator.py
chik/_tests/blockchain/test_lookup_fork_chain.py
chik/_tests/build-init-files.py
chik/_tests/build-job-matrix.py
chik/_tests/check_pytest_monitor_output.py
chik/_tests/check_sql_statements.py
chik/_tests/chik-start-sim
chik/_tests/cmds/__init__.py
chik/_tests/cmds/cmd_test_utils.py
chik/_tests/cmds/config.py
chik/_tests/cmds/conftest.py
chik/_tests/cmds/test_click_types.py
chik/_tests/cmds/test_cmd_framework.py
chik/_tests/cmds/test_cmds_util.py
chik/_tests/cmds/test_daemon.py
chik/_tests/cmds/test_dev_gh.py
chik/_tests/cmds/test_farm_cmd.py
chik/_tests/cmds/test_show.py
chik/_tests/cmds/test_sim.py
chik/_tests/cmds/test_timelock_args.py
chik/_tests/cmds/test_tx_config_args.py
chik/_tests/cmds/testing_classes.py
chik/_tests/cmds/wallet/__init__.py
chik/_tests/cmds/wallet/test_consts.py
chik/_tests/cmds/wallet/test_did.py
chik/_tests/cmds/wallet/test_nft.py
chik/_tests/cmds/wallet/test_notifications.py
chik/_tests/cmds/wallet/test_offer.toffer
chik/_tests/cmds/wallet/test_tx_decorators.py
chik/_tests/cmds/wallet/test_vcs.py
chik/_tests/cmds/wallet/test_wallet.py
chik/_tests/cmds/wallet/test_wallet_check.py
chik/_tests/conftest.py
chik/_tests/connection_utils.py
chik/_tests/core/__init__.py
chik/_tests/core/cmds/__init__.py
chik/_tests/core/cmds/test_beta.py
chik/_tests/core/cmds/test_keys.py
chik/_tests/core/cmds/test_wallet.py
chik/_tests/core/config.py
chik/_tests/core/consensus/__init__.py
chik/_tests/core/consensus/stores/__init__.py
chik/_tests/core/consensus/stores/test_coin_store_protocol.py
chik_blockchain-2.5.6.dist-info/METADATA
chik_blockchain-2.5.6.dist-info/WHEEL
chik_blockchain-2.5.6.dist-info/entry_points.txt
chik_blockchain-2.5.6.dist-info/licenses/LICENSE
chik_blockchain-2.5.6.dist-info/RECORD
