Metadata-Version: 2.4
Name: chik-blockchain
Version: 2.5.6
Summary: Chik blockchain full node, farmer, timelord, and wallet.
License: Apache-2.0
License-File: LICENSE
Keywords: chik,blockchain,node
Author: Mariano Sorgente
Author-email: mariano@chiknetwork.com
Requires-Python: >=3.9, <4
Classifier: License :: OSI Approved :: Apache Software License
Classifier: Programming Language :: Python :: 3
Classifier: Programming Language :: Python :: 3.9
Classifier: Programming Language :: Python :: 3.10
Classifier: Programming Language :: Python :: 3.11
Classifier: Programming Language :: Python :: 3.12
Classifier: Programming Language :: Python :: 3.13
Classifier: Programming Language :: Python :: 3.14
Provides-Extra: dev
Provides-Extra: legacy-keyring
Provides-Extra: upnp
Requires-Dist: aiofiles (>=24.1.0)
Requires-Dist: aiohttp (>=3.10.4)
Requires-Dist: aiohttp_cors (>=0.7.0) ; extra == "dev"
Requires-Dist: aiosqlite (>=0.20.0)
Requires-Dist: anyio (>=4.6.2.post1)
Requires-Dist: bitstring (>=4.1.4)
Requires-Dist: boto3 (>=1.35.43)
Requires-Dist: build (>=1.2.1) ; extra == "dev"
Requires-Dist: chik-puzzles-py (>=0.20.1)
Requires-Dist: chik_rs (>=0.27,<0.28)
Requires-Dist: chikbip158 (>=1.5.2)
Requires-Dist: chikpos (>=2.0.10)
Requires-Dist: chikvdf (>=1.1.10)
Requires-Dist: click (>=8.1.7)
Requires-Dist: colorama (>=0.4.6)
Requires-Dist: colorlog (>=6.9.0)
Requires-Dist: concurrent_log_handler (>=0.9.25)
Requires-Dist: coverage (>=7.6.4) ; extra == "dev"
Requires-Dist: cryptography (>=43.0.1)
Requires-Dist: diff-cover (>=9.2.0) ; extra == "dev"
Requires-Dist: dnslib (>=0.9.25)
Requires-Dist: dnspython (>=2.6.1)
Requires-Dist: filelock (>=3.16.1)
Requires-Dist: hsmk (>=0.3.2)
Requires-Dist: importlib-resources (>=6.4.5)
Requires-Dist: keyring (>=25.5.0)
Requires-Dist: keyrings.cryptfile (>=1.3.9) ; extra == "legacy-keyring"
Requires-Dist: klvm (>=0.9.14)
Requires-Dist: klvm_tools (>=0.4.9)
Requires-Dist: klvm_tools_rs (>=0.1.45)
Requires-Dist: lxml (>=5.2.2) ; extra == "dev"
Requires-Dist: miniupnpc (>=2.3.2,<3) ; extra == "upnp"
Requires-Dist: mypy (>=1.11.1) ; extra == "dev"
Requires-Dist: packaging (>=24.0)
Requires-Dist: pip (>=24.2)
Requires-Dist: pre-commit (>=3.7.1) ; extra == "dev"
Requires-Dist: psutil (>=6.1.0)
Requires-Dist: py3createtorrent (>=1.2.1) ; extra == "dev"
Requires-Dist: pyinstaller (>=6.9.0) ; (python_version < "3.13") and (extra == "dev")
Requires-Dist: pytest (>=8.3.3) ; extra == "dev"
Requires-Dist: pytest-cov (>=5.0.0) ; extra == "dev"
Requires-Dist: pytest-mock (>=3.14.0) ; extra == "dev"
Requires-Dist: pytest-monitor (>=1.6.6) ; (sys_platform == "linux") and (extra == "dev")
Requires-Dist: pytest-xdist (>=3.6.1) ; extra == "dev"
Requires-Dist: pyyaml (>=6.0.2)
Requires-Dist: ruff (>=0.8.1) ; extra == "dev"
Requires-Dist: setproctitle (>=1.3.3)
Requires-Dist: setuptools (>=75.5.0)
Requires-Dist: sortedcontainers (>=2.4.0)
Requires-Dist: tach (>=0.29.0) ; extra == "dev"
Requires-Dist: types-aiofiles (>=24.1.0.20240626) ; extra == "dev"
Requires-Dist: types-cryptography (>=3.3.23.2) ; extra == "dev"
Requires-Dist: types-pyyaml (>=6.0.12.20240917) ; extra == "dev"
Requires-Dist: types-setuptools (>=75.5.0.20241122) ; extra == "dev"
Requires-Dist: typing-extensions (>=4.12.2)
Requires-Dist: watchdog (>=4.0.1)
Requires-Dist: zstd (>=1.5.5.1) ; python_version < "3.12"
Requires-Dist: zstd (>=1.5.5.1) ; python_version == "3.12"
Project-URL: changelog, https://github.com/Chik-Network/chik-blockchain/blob/main/CHANGELOG.md
Project-URL: source, https://github.com/Chik-Network/chik-blockchain/
